mediaserver_api_client-6.2.dist-info/licenses/LICENSE
ms_client/__init__.py
ms_client/client.py
ms_client/conf.py
ms_client/lib/__init__.py
ms_client/lib/configuration.py
ms_client/lib/content.py
ms_client/lib/download.py
ms_client/lib/upload.py
ms_client/lib/users_csv.py
ms_client/lib/utils.py
mediaserver_api_client-6.2.dist-info/METADATA
mediaserver_api_client-6.2.dist-info/WHEEL
mediaserver_api_client-6.2.dist-info/top_level.txt
mediaserver_api_client-6.2.dist-info/RECORD
