Metadata-Version: 2.4
Name: mediaserver-api-client
Version: 6.2
Summary: A python3 reference implementation of an UbiCast MediaServer (Nudgis) API client.
Author: UbiCast
License-Expression: LGPL-3.0-only
Project-URL: Repository, https://github.com/UbiCastTeam/mediaserver-client
Classifier: Development Status :: 5 - Production/Stable
Classifier: Environment :: Console
Classifier: Intended Audience :: Developers
Classifier: Operating System :: OS Independent
Classifier: Programming Language :: Python
Classifier: Programming Language :: Python :: 3 :: Only
Classifier: Topic :: Internet :: WWW/HTTP
Requires-Python: >=3.11
License-File: LICENSE
Requires-Dist: requests>=2.30
Provides-Extra: dev
Requires-Dist: flake8; extra == "dev"
Requires-Dist: mypy; extra == "dev"
Requires-Dist: pytest; extra == "dev"
Requires-Dist: pytest-cov; extra == "dev"
Requires-Dist: types-requests; extra == "dev"
Requires-Dist: vulture; extra == "dev"
Dynamic: license-file
